{
  "seed": 123,
  "cycle": 29,
  "config": {
    "N": 256,
    "M_max": 512,
    "obs_radius": 2,
    "embed_dim": 24,
    "hidden_dim": 16,
    "n_actions": 7,
    "prey_fraction": 0.8,
    "n_patches": 12,
    "patch_radius": 20,
    "patch_min_spacing": 60,
    "patch_regen": 0.003,
    "barren_regen": 0.0,
    "signal_decay": 0.04,
    "signal_diffusion": 0.15,
    "initial_energy": 1.0,
    "resource_value": 1.5,
    "initial_resource": 0.6,
    "prey_metabolic": 0.0004,
    "prey_metabolic_barren": 0.001,
    "pred_metabolic": 0.0008,
    "predation_gain": 0.15,
    "predation_loss": 0.2,
    "stress_regen": 0.0003,
    "mutation_std": 0.03,
    "tournament_size": 4,
    "elite_fraction": 0.5,
    "activate_offspring": true,
    "drought_every": 5,
    "drought_depletion": 0.01,
    "drought_regen": 0.0,
    "chunk_size": 50,
    "steps_per_cycle": 5000,
    "n_cycles": 30,
    "obs_side": 5,
    "obs_flat": 102,
    "n_prey": 409,
    "n_pred": 103,
    "n_params": 4559
  },
  "cycles": [
    {
      "cycle": 0,
      "n_alive_start": 127,
      "n_alive_end": 76,
      "n_prey_start": 102,
      "n_prey_end": 75,
      "n_pred_start": 25,
      "n_pred_end": 1,
      "mean_alive": 98.26279937744141,
      "mean_prey": 89.14419960021972,
      "mean_pred": 9.118599994182587,
      "mortality": 0.4015748031496063,
      "mean_phi": 0.09631087556481362,
      "phi_base": 0.08487936109304428,
      "phi_stress": 0.08158242702484131,
      "robustness": 0.96115741181665,
      "n_alive_base": 76,
      "n_alive_stress": 76,
      "elapsed_s": 0.8133578300476074
    },
    {
      "cycle": 1,
      "n_alive_start": 512,
      "n_alive_end": 442,
      "n_prey_start": 409,
      "n_prey_end": 378,
      "n_pred_start": 103,
      "n_pred_end": 64,
      "mean_alive": 475.6601968383789,
      "mean_prey": 389.85159759521486,
      "mean_pred": 85.80859954833984,
      "mortality": 0.13671875,
      "mean_phi": 0.0925971232354641,
      "phi_base": 0.08766650408506393,
      "phi_stress": 0.08683245927095413,
      "robustness": 0.9904861631838254,
      "n_alive_base": 441,
      "n_alive_stress": 441,
      "elapsed_s": 1.4799046516418457
    },
    {
      "cycle": 2,
      "n_alive_start": 512,
      "n_alive_end": 454,
      "n_prey_start": 409,
      "n_prey_end": 389,
      "n_pred_start": 103,
      "n_pred_end": 65,
      "mean_alive": 483.4489953613281,
      "mean_prey": 397.14759826660156,
      "mean_pred": 86.30139938354492,
      "mortality": 0.11328125,
      "mean_phi": 0.08462142944335938,
      "phi_base": 0.08774743974208832,
      "phi_stress": 0.08471050709486008,
      "robustness": 0.9653900711387757,
      "n_alive_base": 453,
      "n_alive_stress": 453,
      "elapsed_s": 0.7582182884216309
    },
    {
      "cycle": 3,
      "n_alive_start": 512,
      "n_alive_end": 467,
      "n_prey_start": 409,
      "n_prey_end": 385,
      "n_pred_start": 103,
      "n_pred_end": 82,
      "mean_alive": 489.6575979614258,
      "mean_prey": 396.59819885253904,
      "mean_pred": 93.05939971923829,
      "mortality": 0.087890625,
      "mean_phi": 0.09025323241949082,
      "phi_base": 0.08676490038633347,
      "phi_stress": 0.0851926103234291,
      "robustness": 0.9818787314236113,
      "n_alive_base": 467,
      "n_alive_stress": 466,
      "elapsed_s": 0.7711586952209473
    },
    {
      "cycle": 4,
      "n_alive_start": 512,
      "n_alive_end": 455,
      "n_prey_start": 409,
      "n_prey_end": 378,
      "n_pred_start": 103,
      "n_pred_end": 77,
      "mean_alive": 482.52619689941406,
      "mean_prey": 392.47099822998047,
      "mean_pred": 90.05519966125489,
      "mortality": 0.111328125,
      "mean_phi": 0.08206985294818878,
      "phi_base": 0.0776935487985611,
      "phi_stress": 0.07578645944595337,
      "robustness": 0.9754536974806969,
      "n_alive_base": 451,
      "n_alive_stress": 451,
      "elapsed_s": 0.7630255222320557
    },
    {
      "cycle": 5,
      "n_alive_start": 512,
      "n_alive_end": 0,
      "n_prey_start": 409,
      "n_prey_end": 0,
      "n_pred_start": 103,
      "n_pred_end": 0,
      "mean_alive": 146.87519784152508,
      "mean_prey": 100.35059855043887,
      "mean_pred": 46.5245998686552,
      "mortality": 1.0,
      "mean_phi": 0.09247181043028832,
      "phi_base": 0.0,
      "phi_stress": 0.0,
      "robustness": 0.0,
      "n_alive_base": 0,
      "n_alive_stress": 0,
      "elapsed_s": 0.7958893775939941
    },
    {
      "cycle": 6,
      "n_alive_start": 510,
      "n_alive_end": 386,
      "n_prey_start": 408,
      "n_prey_end": 375,
      "n_pred_start": 102,
      "n_pred_end": 11,
      "mean_alive": 424.0789962768555,
      "mean_prey": 379.65779846191407,
      "mean_pred": 44.42119989395142,
      "mortality": 0.24313725490196078,
      "mean_phi": 0.041570867598056796,
      "phi_base": 0.04337627664208412,
      "phi_stress": 0.04435367807745934,
      "robustness": 1.0225330874625356,
      "n_alive_base": 385,
      "n_alive_stress": 385,
      "elapsed_s": 0.7596733570098877
    },
    {
      "cycle": 7,
      "n_alive_start": 512,
      "n_alive_end": 424,
      "n_prey_start": 409,
      "n_prey_end": 390,
      "n_pred_start": 103,
      "n_pred_end": 34,
      "mean_alive": 460.9459963989258,
      "mean_prey": 396.6621987915039,
      "mean_pred": 64.28379978179932,
      "mortality": 0.171875,
      "mean_phi": 0.051764626801013944,
      "phi_base": 0.0470603808760643,
      "phi_stress": 0.048307813704013824,
      "robustness": 1.0265070703791093,
      "n_alive_base": 422,
      "n_alive_stress": 422,
      "elapsed_s": 0.7600152492523193
    },
    {
      "cycle": 8,
      "n_alive_start": 512,
      "n_alive_end": 412,
      "n_prey_start": 409,
      "n_prey_end": 364,
      "n_pred_start": 103,
      "n_pred_end": 48,
      "mean_alive": 459.456794128418,
      "mean_prey": 380.77579681396486,
      "mean_pred": 78.68099956512451,
      "mortality": 0.1953125,
      "mean_phi": 0.049280932545661925,
      "phi_base": 0.046220697462558746,
      "phi_stress": 0.046794401854276656,
      "robustness": 1.0124122833105804,
      "n_alive_base": 411,
      "n_alive_stress": 411,
      "elapsed_s": 0.7451503276824951
    },
    {
      "cycle": 9,
      "n_alive_start": 512,
      "n_alive_end": 428,
      "n_prey_start": 409,
      "n_prey_end": 371,
      "n_pred_start": 103,
      "n_pred_end": 57,
      "mean_alive": 466.7469955444336,
      "mean_prey": 386.62839782714843,
      "mean_pred": 80.11859966278077,
      "mortality": 0.1640625,
      "mean_phi": 0.051387495920062067,
      "phi_base": 0.049620022624731065,
      "phi_stress": 0.050505556911230085,
      "robustness": 1.0178463096076393,
      "n_alive_base": 427,
      "n_alive_stress": 427,
      "elapsed_s": 0.7612965106964111
    },
    {
      "cycle": 10,
      "n_alive_start": 512,
      "n_alive_end": 0,
      "n_prey_start": 409,
      "n_prey_end": 0,
      "n_pred_start": 103,
      "n_pred_end": 0,
      "mean_alive": 145.8023964777589,
      "mean_prey": 100.1697970199585,
      "mean_pred": 45.632599896490575,
      "mortality": 1.0,
      "mean_phi": 0.05146133825182915,
      "phi_base": 0.0,
      "phi_stress": 0.0,
      "robustness": 0.0,
      "n_alive_base": 0,
      "n_alive_stress": 0,
      "elapsed_s": 0.8003978729248047
    },
    {
      "cycle": 11,
      "n_alive_start": 510,
      "n_alive_end": 344,
      "n_prey_start": 408,
      "n_prey_end": 332,
      "n_pred_start": 102,
      "n_pred_end": 12,
      "mean_alive": 440.6833953857422,
      "mean_prey": 380.722197265625,
      "mean_pred": 59.9611997127533,
      "mortality": 0.3254901960784314,
      "mean_phi": 0.036896008625626565,
      "phi_base": 0.035797927528619766,
      "phi_stress": 0.03528348207473755,
      "robustness": 0.9856291833243439,
      "n_alive_base": 341,
      "n_alive_stress": 341,
      "elapsed_s": 0.7700753211975098
    },
    {
      "cycle": 12,
      "n_alive_start": 512,
      "n_alive_end": 368,
      "n_prey_start": 409,
      "n_prey_end": 345,
      "n_pred_start": 103,
      "n_pred_end": 23,
      "mean_alive": 440.9327938842773,
      "mean_prey": 378.7749966430664,
      "mean_pred": 62.157799587249755,
      "mortality": 0.28125,
      "mean_phi": 0.03756535090506077,
      "phi_base": 0.03407180160284042,
      "phi_stress": 0.03440756946802139,
      "robustness": 1.0098547141444079,
      "n_alive_base": 360,
      "n_alive_stress": 360,
      "elapsed_s": 0.7761163711547852
    },
    {
      "cycle": 13,
      "n_alive_start": 512,
      "n_alive_end": 374,
      "n_prey_start": 409,
      "n_prey_end": 344,
      "n_pred_start": 103,
      "n_pred_end": 30,
      "mean_alive": 445.52959533691404,
      "mean_prey": 379.33459625244143,
      "mean_pred": 66.19499969482422,
      "mortality": 0.26953125,
      "mean_phi": 0.042319095507264134,
      "phi_base": 0.04165962263941765,
      "phi_stress": 0.04045843631029129,
      "robustness": 0.9711666536319075,
      "n_alive_base": 370,
      "n_alive_stress": 370,
      "elapsed_s": 0.7412734031677246
    },
    {
      "cycle": 14,
      "n_alive_start": 512,
      "n_alive_end": 382,
      "n_prey_start": 409,
      "n_prey_end": 348,
      "n_pred_start": 103,
      "n_pred_end": 34,
      "mean_alive": 442.90319396972654,
      "mean_prey": 375.7447967529297,
      "mean_pred": 67.1583996963501,
      "mortality": 0.25390625,
      "mean_phi": 0.04093218185007572,
      "phi_base": 0.0392424575984478,
      "phi_stress": 0.038255729526281354,
      "robustness": 0.9748555994565061,
      "n_alive_base": 378,
      "n_alive_stress": 377,
      "elapsed_s": 0.7710671424865723
    },
    {
      "cycle": 15,
      "n_alive_start": 512,
      "n_alive_end": 0,
      "n_prey_start": 409,
      "n_prey_end": 0,
      "n_pred_start": 103,
      "n_pred_end": 0,
      "mean_alive": 149.58579676374794,
      "mean_prey": 102.03759805679321,
      "mean_pred": 47.54819989904761,
      "mortality": 1.0,
      "mean_phi": 0.034224465605802834,
      "phi_base": 0.0,
      "phi_stress": 0.0,
      "robustness": 0.0,
      "n_alive_base": 0,
      "n_alive_stress": 0,
      "elapsed_s": 0.7977681159973145
    },
    {
      "cycle": 16,
      "n_alive_start": 510,
      "n_alive_end": 355,
      "n_prey_start": 408,
      "n_prey_end": 338,
      "n_pred_start": 102,
      "n_pred_end": 17,
      "mean_alive": 430.041194152832,
      "mean_prey": 373.4259957885742,
      "mean_pred": 56.615199699401856,
      "mortality": 0.30392156862745096,
      "mean_phi": 0.05873102061450482,
      "phi_base": 0.0629838153719902,
      "phi_stress": 0.06375961452722549,
      "robustness": 1.01231743664072,
      "n_alive_base": 351,
      "n_alive_stress": 351,
      "elapsed_s": 0.7698328495025635
    },
    {
      "cycle": 17,
      "n_alive_start": 512,
      "n_alive_end": 371,
      "n_prey_start": 409,
      "n_prey_end": 341,
      "n_pred_start": 103,
      "n_pred_end": 30,
      "mean_alive": 438.6271939086914,
      "mean_prey": 377.7479962158203,
      "mean_pred": 60.87919981002808,
      "mortality": 0.275390625,
      "mean_phi": 0.0575373686850071,
      "phi_base": 0.056116464734077456,
      "phi_stress": 0.05687650591135025,
      "robustness": 1.0135439960602375,
      "n_alive_base": 362,
      "n_alive_stress": 362,
      "elapsed_s": 0.7642834186553955
    },
    {
      "cycle": 18,
      "n_alive_start": 512,
      "n_alive_end": 394,
      "n_prey_start": 409,
      "n_prey_end": 364,
      "n_pred_start": 103,
      "n_pred_end": 30,
      "mean_alive": 447.34339630126954,
      "mean_prey": 383.0827981567383,
      "mean_pred": 64.26059965133668,
      "mortality": 0.23046875,
      "mean_phi": 0.05769468694925308,
      "phi_base": 0.059576119482517245,
      "phi_stress": 0.060424665361642836,
      "robustness": 1.0142430538695055,
      "n_alive_base": 393,
      "n_alive_stress": 393,
      "elapsed_s": 0.7638921737670898
    },
    {
      "cycle": 19,
      "n_alive_start": 512,
      "n_alive_end": 375,
      "n_prey_start": 409,
      "n_prey_end": 336,
      "n_pred_start": 103,
      "n_pred_end": 39,
      "mean_alive": 442.7069952392578,
      "mean_prey": 372.7907974243164,
      "mean_pred": 69.91619960784912,
      "mortality": 0.267578125,
      "mean_phi": 0.059025499224662784,
      "phi_base": 0.06457239463925361,
      "phi_stress": 0.06554481461644172,
      "robustness": 1.0150593761098798,
      "n_alive_base": 373,
      "n_alive_stress": 372,
      "elapsed_s": 0.7620494365692139
    },
    {
      "cycle": 20,
      "n_alive_start": 512,
      "n_alive_end": 1,
      "n_prey_start": 409,
      "n_prey_end": 1,
      "n_pred_start": 103,
      "n_pred_end": 0,
      "mean_alive": 144.29139679074288,
      "mean_prey": 100.0087979400158,
      "mean_pred": 44.28259983778,
      "mortality": 0.998046875,
      "mean_phi": 0.046943818032741544,
      "phi_base": 0.0,
      "phi_stress": 0.0,
      "robustness": 0.0,
      "n_alive_base": 0,
      "n_alive_stress": 0,
      "elapsed_s": 0.7920620441436768
    },
    {
      "cycle": 21,
      "n_alive_start": 511,
      "n_alive_end": 414,
      "n_prey_start": 409,
      "n_prey_end": 403,
      "n_pred_start": 102,
      "n_pred_end": 11,
      "mean_alive": 450.75339782714843,
      "mean_prey": 406.5039996337891,
      "mean_pred": 44.24939989089966,
      "mortality": 0.1898238747553816,
      "mean_phi": 0.03128354586660862,
      "phi_base": 0.029544925317168236,
      "phi_stress": 0.0253800205886364,
      "robustness": 0.8590314687269948,
      "n_alive_base": 412,
      "n_alive_stress": 412,
      "elapsed_s": 0.7690610885620117
    },
    {
      "cycle": 22,
      "n_alive_start": 512,
      "n_alive_end": 411,
      "n_prey_start": 409,
      "n_prey_end": 388,
      "n_pred_start": 103,
      "n_pred_end": 23,
      "mean_alive": 455.7479962158203,
      "mean_prey": 398.7705987548828,
      "mean_pred": 56.977399826049805,
      "mortality": 0.197265625,
      "mean_phi": 0.03696892745792866,
      "phi_base": 0.034140437841415405,
      "phi_stress": 0.032297082245349884,
      "robustness": 0.9460066796850107,
      "n_alive_base": 408,
      "n_alive_stress": 408,
      "elapsed_s": 0.7582781314849854
    },
    {
      "cycle": 23,
      "n_alive_start": 512,
      "n_alive_end": 402,
      "n_prey_start": 409,
      "n_prey_end": 383,
      "n_pred_start": 103,
      "n_pred_end": 19,
      "mean_alive": 457.63299682617185,
      "mean_prey": 395.60679809570314,
      "mean_pred": 62.02619983673096,
      "mortality": 0.21484375,
      "mean_phi": 0.04287660904228687,
      "phi_base": 0.04129914939403534,
      "phi_stress": 0.04009382203221321,
      "robustness": 0.9708147170218424,
      "n_alive_base": 400,
      "n_alive_stress": 399,
      "elapsed_s": 0.7525420188903809
    },
    {
      "cycle": 24,
      "n_alive_start": 512,
      "n_alive_end": 427,
      "n_prey_start": 409,
      "n_prey_end": 391,
      "n_pred_start": 103,
      "n_pred_end": 36,
      "mean_alive": 469.69599609375,
      "mean_prey": 399.848798828125,
      "mean_pred": 69.84719970703125,
      "mortality": 0.166015625,
      "mean_phi": 0.045431087911129,
      "phi_base": 0.04737702012062073,
      "phi_stress": 0.04480017125606537,
      "robustness": 0.945609731089149,
      "n_alive_base": 426,
      "n_alive_stress": 426,
      "elapsed_s": 0.7283260822296143
    },
    {
      "cycle": 25,
      "n_alive_start": 512,
      "n_alive_end": 0,
      "n_prey_start": 409,
      "n_prey_end": 0,
      "n_pred_start": 103,
      "n_pred_end": 0,
      "mean_alive": 151.10699679717422,
      "mean_prey": 100.98159797638655,
      "mean_pred": 50.12539985045791,
      "mortality": 1.0,
      "mean_phi": 0.03255521321843844,
      "phi_base": 0.0,
      "phi_stress": 0.0,
      "robustness": 0.0,
      "n_alive_base": 0,
      "n_alive_stress": 0,
      "elapsed_s": 0.7995469570159912
    },
    {
      "cycle": 26,
      "n_alive_start": 510,
      "n_alive_end": 477,
      "n_prey_start": 408,
      "n_prey_end": 406,
      "n_pred_start": 102,
      "n_pred_end": 71,
      "mean_alive": 494.48019805908206,
      "mean_prey": 407.0349996948242,
      "mean_pred": 87.44519958496093,
      "mortality": 0.06470588235294118,
      "mean_phi": 0.030833553336560727,
      "phi_base": 0.028964795544743537,
      "phi_stress": 0.029188134148716925,
      "robustness": 1.0077106915403005,
      "n_alive_base": 477,
      "n_alive_stress": 477,
      "elapsed_s": 0.7676131725311279
    },
    {
      "cycle": 27,
      "n_alive_start": 512,
      "n_alive_end": 466,
      "n_prey_start": 409,
      "n_prey_end": 404,
      "n_pred_start": 103,
      "n_pred_end": 62,
      "mean_alive": 491.7731973266602,
      "mean_prey": 407.12859985351565,
      "mean_pred": 84.644599609375,
      "mortality": 0.08984375,
      "mean_phi": 0.036181125417351724,
      "phi_base": 0.034761594235897066,
      "phi_stress": 0.03466358929872513,
      "robustness": 0.9971806547045322,
      "n_alive_base": 466,
      "n_alive_stress": 466,
      "elapsed_s": 0.7602338790893555
    },
    {
      "cycle": 28,
      "n_alive_start": 512,
      "n_alive_end": 465,
      "n_prey_start": 409,
      "n_prey_end": 404,
      "n_pred_start": 103,
      "n_pred_end": 61,
      "mean_alive": 495.5779977416992,
      "mean_prey": 407.89539978027346,
      "mean_pred": 87.68259956359863,
      "mortality": 0.091796875,
      "mean_phi": 0.04202733188867569,
      "phi_base": 0.04071148857474327,
      "phi_stress": 0.039585371315479276,
      "robustness": 0.9723390792454929,
      "n_alive_base": 462,
      "n_alive_stress": 464,
      "elapsed_s": 0.7708756923675537
    },
    {
      "cycle": 29,
      "n_alive_start": 512,
      "n_alive_end": 475,
      "n_prey_start": 409,
      "n_prey_end": 403,
      "n_pred_start": 103,
      "n_pred_end": 72,
      "mean_alive": 496.2113980102539,
      "mean_prey": 406.62719970703125,
      "mean_pred": 89.58419960021973,
      "mortality": 0.072265625,
      "mean_phi": 0.042366648092865944,
      "phi_base": 0.03968359082937241,
      "phi_stress": 0.038729113340377805,
      "robustness": 0.9759478043935447,
      "n_alive_base": 474,
      "n_alive_stress": 474,
      "elapsed_s": 0.7640681266784668
    }
  ],
  "snapshots": [
    {
      "cycle": 0,
      "path": "results/v25_s123/snapshot_c00.npz"
    },
    {
      "cycle": 5,
      "path": "results/v25_s123/snapshot_c05.npz"
    },
    {
      "cycle": 10,
      "path": "results/v25_s123/snapshot_c10.npz"
    },
    {
      "cycle": 15,
      "path": "results/v25_s123/snapshot_c15.npz"
    },
    {
      "cycle": 20,
      "path": "results/v25_s123/snapshot_c20.npz"
    },
    {
      "cycle": 25,
      "path": "results/v25_s123/snapshot_c25.npz"
    },
    {
      "cycle": 29,
      "path": "results/v25_s123/snapshot_c29.npz"
    }
  ]
}