{
  "metadata": {
    "snapshot_path": "/Users/jacob/fun/shape-of-experience/empirical/experiments/study_ca_affect/results/v13_s42_v2/v13_s42_v2/snapshots/cycle_029.npz",
    "seed": 42,
    "C": 16,
    "N": 128,
    "n_recording_steps": 50,
    "tau_values": [
      1,
      2,
      5,
      10
    ],
    "n_patterns_detected": 44,
    "n_patterns_analyzed": 20,
    "cycle": 29
  },
  "patterns": [
    {
      "pattern_id": 0,
      "n_timesteps": 50,
      "rho_self": 0.0,
      "SM": {
        "1": -13.451482913297156,
        "2": -158.28960467783216,
        "5": -324.2765685055757,
        "10": -5.453979827318045
      },
      "SM_capacity": 0.0,
      "SM_sal": 0.0,
      "f_self_mse": {
        "1": 47.86623175479111,
        "2": 183.988343651799,
        "5": 333.88196553645275,
        "10": 7.983257471446978
      },
      "f_ext_mse": {
        "1": 34.41474884149395,
        "2": 25.69873897396684,
        "5": 9.605397030877015,
        "10": 2.5292776441289337
      }
    },
    {
      "pattern_id": 1,
      "n_timesteps": 50,
      "rho_self": 0.0,
      "SM": {
        "1": -18.20133199858428,
        "2": -382.76510518031034,
        "5": -58.00280201285082,
        "10": -11.819928488512126
      },
      "SM_capacity": 0.0,
      "SM_sal": 0.0,
      "f_self_mse": {
        "1": 64.17042666609113,
        "2": 435.0181805106131,
        "5": 152.13791846460907,
        "10": 70.95911357753218
      },
      "f_ext_mse": {
        "1": 45.96909466750685,
        "2": 52.253075330302735,
        "5": 94.13511645175825,
        "10": 59.13918508902005
      }
    },
    {
      "pattern_id": 2,
      "n_timesteps": 50,
      "rho_self": 0.0,
      "SM": {
        "1": -8277.084493153176,
        "2": -663.959045838516,
        "5": -4348.4442503924,
        "10": -12430.751925451226
      },
      "SM_capacity": 0.0,
      "SM_sal": 0.0,
      "f_self_mse": {
        "1": 8492.455284749001,
        "2": 872.5883324737321,
        "5": 4497.421590966081,
        "10": 12582.44920614705
      },
      "f_ext_mse": {
        "1": 215.37079159582595,
        "2": 208.62928663521615,
        "5": 148.97734057368024,
        "10": 151.69728069582465
      }
    },
    {
      "pattern_id": 3,
      "n_timesteps": 50,
      "rho_self": 0.0,
      "SM": {
        "1": -9.210941867993458,
        "2": -15.671180576768364,
        "5": -376.96532067924215,
        "10": -36.151082809606464
      },
      "SM_capacity": 0.0,
      "SM_sal": 0.0,
      "f_self_mse": {
        "1": 24.08768425809776,
        "2": 52.81264343457751,
        "5": 419.0293716931894,
        "10": 48.21179733811945
      },
      "f_ext_mse": {
        "1": 14.876742390104301,
        "2": 37.141462857809145,
        "5": 42.064051013947235,
        "10": 12.060714528512992
      }
    },
    {
      "pattern_id": 4,
      "n_timesteps": 50,
      "rho_self": 0.0,
      "SM": {
        "1": -147.14247089867533,
        "2": -232.30263097911592,
        "5": -999.5310432362794,
        "10": -225.75801245788634
      },
      "SM_capacity": 0.0,
      "SM_sal": 0.0,
      "f_self_mse": {
        "1": 236.18974939328137,
        "2": 325.55773858196943,
        "5": 1119.1692750716531,
        "10": 336.56501678328925
      },
      "f_ext_mse": {
        "1": 89.04727849460605,
        "2": 93.25510760285351,
        "5": 119.6382318353737,
        "10": 110.80700432540291
      }
    },
    {
      "pattern_id": 5,
      "n_timesteps": 50,
      "rho_self": 0.0,
      "SM": {
        "1": -8.359239325105335,
        "2": -55.92851149747466,
        "5": 16.768111606385034,
        "10": -1193.9504093504681
      },
      "SM_capacity": 67.07244642554014,
      "SM_sal": 0.0,
      "f_self_mse": {
        "1": 26.418927632215123,
        "2": 89.80932966388039,
        "5": 34.97197289789155,
        "10": 1234.5590977917138
      },
      "f_ext_mse": {
        "1": 18.059688307109788,
        "2": 33.88081816640573,
        "5": 51.74008450427658,
        "10": 40.608688441245654
      }
    },
    {
      "pattern_id": 6,
      "n_timesteps": 50,
      "rho_self": 0.0,
      "SM": {
        "1": -1.3804552083387875,
        "2": -20.566265847973355,
        "5": -6.713486741398107,
        "10": -140.19196956796426
      },
      "SM_capacity": 0.0,
      "SM_sal": Infinity,
      "f_self_mse": {
        "1": 86.26047407986763,
        "2": 92.21791361164534,
        "5": 64.00587739210692,
        "10": 179.86397305937285
      },
      "f_ext_mse": {
        "1": 84.88001887152885,
        "2": 71.65164776367199,
        "5": 57.29239065070882,
        "10": 39.672003491408596
      }
    },
    {
      "pattern_id": 7,
      "n_timesteps": 50,
      "rho_self": 0.0,
      "SM": {
        "1": -46.25098234507949,
        "2": -130.69396205998612,
        "5": -263.68206226312424,
        "10": -4.822359342601004
      },
      "SM_capacity": 0.0,
      "SM_sal": 0.0,
      "f_self_mse": {
        "1": 137.08993865239535,
        "2": 198.19063819808827,
        "5": 318.7015401823002,
        "10": 64.78833472664743
      },
      "f_ext_mse": {
        "1": 90.83895630731585,
        "2": 67.49667613810216,
        "5": 55.019477919176,
        "10": 59.96597538404643
      }
    },
    {
      "pattern_id": 8,
      "n_timesteps": 50,
      "rho_self": 0.0,
      "SM": {
        "1": 1.5156389310252136,
        "2": -1.9992411514454718,
        "5": -8.911083357452043,
        "10": -553.5830594741155
      },
      "SM_capacity": 0.7578194655126068,
      "SM_sal": Infinity,
      "f_self_mse": {
        "1": 1.9895034937819667,
        "2": 6.140250599112973,
        "5": 15.15213738595059,
        "10": 559.7867536112378
      },
      "f_ext_mse": {
        "1": 3.5051424248071803,
        "2": 4.141009447667502,
        "5": 6.241054028498548,
        "10": 6.20369413712224
      }
    },
    {
      "pattern_id": 9,
      "n_timesteps": 50,
      "rho_self": 0.0,
      "SM": {
        "1": 58.36107370333474,
        "2": 55.36762324385823,
        "5": 24.664827033281185,
        "10": -318.80808416111233
      },
      "SM_capacity": 238.57509147250857,
      "SM_sal": Infinity,
      "f_self_mse": {
        "1": 19.26605474914749,
        "2": 26.041972602261126,
        "5": 51.972155269638804,
        "10": 384.9677703457279
      },
      "f_ext_mse": {
        "1": 77.62712845248222,
        "2": 81.40959584611936,
        "5": 76.63698230291999,
        "10": 66.15968618461555
      }
    },
    {
      "pattern_id": 10,
      "n_timesteps": 50,
      "rho_self": 0.0,
      "SM": {
        "1": -6.348498269033648,
        "2": -388.0264306018518,
        "5": -254.65295055225397,
        "10": 35.55350890082201
      },
      "SM_capacity": 88.88377225205502,
      "SM_sal": 0.0,
      "f_self_mse": {
        "1": 35.59859061695094,
        "2": 443.6658864887175,
        "5": 297.4793810505361,
        "10": 146.81195292128717
      },
      "f_ext_mse": {
        "1": 29.250092347917295,
        "2": 55.639455886865676,
        "5": 42.82643049828214,
        "10": 182.36546182210918
      }
    },
    {
      "pattern_id": 11,
      "n_timesteps": 50,
      "rho_self": 0.37397419715812,
      "SM": {
        "1": 9.609147916050848,
        "2": 7.522260721947575,
        "5": 5.892435945057164,
        "10": -4.536960821277037
      },
      "SM_capacity": 43.41883918214923,
      "SM_sal": Infinity,
      "f_self_mse": {
        "1": 1.7358934702021664,
        "2": 1.4028249417629721,
        "5": 1.4777693372431522,
        "10": 7.954767618907286
      },
      "f_ext_mse": {
        "1": 11.345041386253014,
        "2": 8.925085663710547,
        "5": 7.370205282300316,
        "10": 3.4178067976302486
      }
    },
    {
      "pattern_id": 12,
      "n_timesteps": 50,
      "rho_self": 0.0,
      "SM": {
        "1": -307.3028760660821,
        "2": -1.7859018540561777,
        "5": -219.7168066497978,
        "10": -781.2023854775774
      },
      "SM_capacity": 0.0,
      "SM_sal": 0.0,
      "f_self_mse": {
        "1": 374.95341843957203,
        "2": 111.78898874146383,
        "5": 284.936380417387,
        "10": 817.7666577452009
      },
      "f_ext_mse": {
        "1": 67.65054237348993,
        "2": 110.00308688740765,
        "5": 65.2195737675892,
        "10": 36.56427226762345
      }
    },
    {
      "pattern_id": 13,
      "n_timesteps": 50,
      "rho_self": 0.0,
      "SM": {
        "1": -1.3353356388078623,
        "2": -76.06412707482966,
        "5": -150.7428416796553,
        "10": -1263.502218939547
      },
      "SM_capacity": 0.0,
      "SM_sal": Infinity,
      "f_self_mse": {
        "1": 91.87023917802506,
        "2": 179.8548199438066,
        "5": 241.04065010985838,
        "10": 1343.5935748515792
      },
      "f_ext_mse": {
        "1": 90.5349035392172,
        "2": 103.79069286897695,
        "5": 90.29780843020308,
        "10": 80.09135591203221
      }
    },
    {
      "pattern_id": 14,
      "n_timesteps": 50,
      "rho_self": 0.0,
      "SM": {
        "1": 2.4554348578476204,
        "2": 2.1856474058725075,
        "5": 0.23583192181868817,
        "10": -0.5783665311172281
      },
      "SM_capacity": 6.542339927943577,
      "SM_sal": Infinity,
      "f_self_mse": {
        "1": 2.5487252566437895,
        "2": 2.630891006530022,
        "5": 3.19231619451625,
        "10": 1.8546608120818735
      },
      "f_ext_mse": {
        "1": 5.00416011449141,
        "2": 4.8165384124025294,
        "5": 3.4281481163349383,
        "10": 1.2762942809646454
      }
    },
    {
      "pattern_id": 15,
      "n_timesteps": 50,
      "rho_self": 0.12201460966601663,
      "SM": {
        "1": -33.821552428628024,
        "2": -161.79154558727194,
        "5": 8.608131935041616,
        "10": -12743.129359237166
      },
      "SM_capacity": 34.432527740166464,
      "SM_sal": 0.0,
      "f_self_mse": {
        "1": 49.22967930799187,
        "2": 178.82390284626433,
        "5": 5.883419280594961,
        "10": 12754.659618352809
      },
      "f_ext_mse": {
        "1": 15.408126879363845,
        "2": 17.032357258992384,
        "5": 14.491551215636576,
        "10": 11.530259115642881
      }
    },
    {
      "pattern_id": 16,
      "n_timesteps": 50,
      "rho_self": 0.0,
      "SM": {
        "1": 6.814088324509369,
        "2": 7.9773992872171124,
        "5": 5.01749528438288,
        "10": 2.261368787758091
      },
      "SM_capacity": 45.08524584361565,
      "SM_sal": 0.11176736455040766,
      "f_self_mse": {
        "1": 1.702251176068574,
        "2": 2.1395601720942508,
        "5": 3.1059611572614316,
        "10": 2.5207000397651775
      },
      "f_ext_mse": {
        "1": 8.516339500577942,
        "2": 10.116959459311364,
        "5": 8.123456441644311,
        "10": 4.782068827523268
      }
    },
    {
      "pattern_id": 17,
      "n_timesteps": 50,
      "rho_self": 0.0,
      "SM": {
        "1": -165.2253078775404,
        "2": -1.6063774225883307,
        "5": 19.095356097940048,
        "10": -27.03632320711415
      },
      "SM_capacity": 76.38142439176019,
      "SM_sal": 0.0,
      "f_self_mse": {
        "1": 214.87387174327873,
        "2": 39.66890258538559,
        "5": 33.64917654697087,
        "10": 75.74237266251059
      },
      "f_ext_mse": {
        "1": 49.64856386573833,
        "2": 38.06252516279726,
        "5": 52.74453264491092,
        "10": 48.70604945539644
      }
    },
    {
      "pattern_id": 18,
      "n_timesteps": 50,
      "rho_self": 0.0,
      "SM": {
        "1": -54.06337005386938,
        "2": -76.51397055276622,
        "5": 76.53470536593576,
        "10": 4.579229190675447
      },
      "SM_capacity": 317.58689444043165,
      "SM_sal": 0.0,
      "f_self_mse": {
        "1": 138.63884638297415,
        "2": 160.4235044620269,
        "5": 50.74023235355859,
        "10": 15.874844065985192
      },
      "f_ext_mse": {
        "1": 84.57547632910477,
        "2": 83.90953390926067,
        "5": 127.27493771949435,
        "10": 20.45407325666064
      }
    },
    {
      "pattern_id": 19,
      "n_timesteps": 50,
      "rho_self": 0.0,
      "SM": {
        "1": 0.4226899575167469,
        "2": -10.040796819000104,
        "5": -22.45620940342315,
        "10": -3.106372185308978
      },
      "SM_capacity": 0.21134497875837344,
      "SM_sal": Infinity,
      "f_self_mse": {
        "1": 4.1253685542791,
        "2": 15.843111102674367,
        "5": 24.638425427968812,
        "10": 6.405202376309477
      },
      "f_ext_mse": {
        "1": 4.548058511795847,
        "2": 5.8023142836742645,
        "5": 2.1822160245456628,
        "10": 3.298830191000499
      }
    }
  ],
  "summary": {
    "mean_rho_self": 0.024799440341206833,
    "mean_SM_capacity": 45.947387306022065,
    "mean_SM_sal": 0.00859748958080059,
    "n_with_self_model": 11,
    "n_with_high_rho": 2,
    "n_with_salience": 0,
    "mean_SM_by_tau": {
      "1": -450.50001321769633,
      "2": -115.24758835314458,
      "5": -343.86392651418055,
      "10": -1485.099434522533
    }
  },
  "cycle": 29
}